dask_mongo/__init__.py
dask_mongo/_version.py
dask_mongo/core.py
dask_mongo/tests/test_core.py
dask_mongo-2022.5.0.dist-info/LICENSE
dask_mongo-2022.5.0.dist-info/METADATA
dask_mongo-2022.5.0.dist-info/WHEEL
dask_mongo-2022.5.0.dist-info/top_level.txt
dask_mongo-2022.5.0.dist-info/RECORD
