Metadata-Version: 2.1
Name: dask-mongo
Version: 2022.5.0
Summary: Dask + Mongo intergration
Home-page: UNKNOWN
License: BSD
Platform: UNKNOWN
Requires-Python: >=3.8
Requires-Dist: dask
Requires-Dist: distributed
Requires-Dist: pymongo
Provides-Extra: test
Requires-Dist: pytest ; extra == 'test'
